<mediawiki xmlns="http://www.mediawiki.org/xml/export-0.11/" xmlns:xsi="http://www.w3.org/2001/XMLSchema-instance" xsi:schemaLocation="http://www.mediawiki.org/xml/export-0.11/ http://www.mediawiki.org/xml/export-0.11.xsd" version="0.11" xml:lang="en">
  <siteinfo>
    <sitename>Evolutionism Wiki</sitename>
    <dbname>evolutionismwiki</dbname>
    <base>https://evolutionism.miraheze.org/wiki/Main_Page</base>
    <generator>MediaWiki 1.43.1</generator>
    <case>first-letter</case>
    <namespaces>
      <namespace key="-2" case="first-letter">Media</namespace>
      <namespace key="-1" case="first-letter">Special</namespace>
      <namespace key="0" case="first-letter" />
      <namespace key="1" case="first-letter">Talk</namespace>
      <namespace key="2" case="first-letter">User</namespace>
      <namespace key="3" case="first-letter">User talk</namespace>
      <namespace key="4" case="first-letter">Evolutionism Wiki</namespace>
      <namespace key="5" case="first-letter">Evolutionism Wiki talk</namespace>
      <namespace key="6" case="first-letter">File</namespace>
      <namespace key="7" case="first-letter">File talk</namespace>
      <namespace key="8" case="first-letter">MediaWiki</namespace>
      <namespace key="9" case="first-letter">MediaWiki talk</namespace>
      <namespace key="10" case="first-letter">Template</namespace>
      <namespace key="11" case="first-letter">Template talk</namespace>
      <namespace key="12" case="first-letter">Help</namespace>
      <namespace key="13" case="first-letter">Help talk</namespace>
      <namespace key="14" case="first-letter">Category</namespace>
      <namespace key="15" case="first-letter">Category talk</namespace>
      <namespace key="146" case="first-letter">Lexeme</namespace>
      <namespace key="147" case="first-letter">Lexeme talk</namespace>
      <namespace key="460" case="first-letter">Campaign</namespace>
      <namespace key="461" case="first-letter">Campaign talk</namespace>
      <namespace key="828" case="first-letter">Module</namespace>
      <namespace key="829" case="first-letter">Module talk</namespace>
      <namespace key="860" case="first-letter">Item</namespace>
      <namespace key="861" case="first-letter">Item talk</namespace>
      <namespace key="862" case="first-letter">Property</namespace>
      <namespace key="863" case="first-letter">Property talk</namespace>
      <namespace key="1198" case="first-letter">Translations</namespace>
      <namespace key="1199" case="first-letter">Translations talk</namespace>
      <namespace key="3000" case="first-letter">Appendix</namespace>
      <namespace key="3001" case="first-letter">Appendix talk</namespace>
      <namespace key="3002" case="first-letter">Portal</namespace>
      <namespace key="3003" case="first-letter">Portal talk</namespace>
      <namespace key="3004" case="first-letter">Prompt</namespace>
      <namespace key="3005" case="first-letter">Prompt talk</namespace>
      <namespace key="3006" case="first-letter">Notes</namespace>
      <namespace key="3007" case="first-letter">Notes talk</namespace>
    </namespaces>
  </siteinfo>
  <page>
    <title>Property:P1</title>
    <ns>862</ns>
    <id>17345</id>
    <revision>
      <id>175479</id>
      <timestamp>2025-08-10T09:14:15Z</timestamp>
      <contributor>
        <username>Immanuelle</username>
        <id>2</id>
      </contributor>
      <comment>/* wbeditentity-create:2|en */ Parents</comment>
      <origin>175479</origin>
      <model>wikibase-property</model>
      <format>application/json</format>
      <text bytes="151" sha1="r0tbmxhyqif8owr5zozu2fovaxp8b8j" xml:space="preserve">{"type":"property","datatype":"wikibase-item","id":"P1","labels":{"en":{"language":"en","value":"Parents"}},"descriptions":[],"aliases":[],"claims":[]}</text>
      <sha1>r0tbmxhyqif8owr5zozu2fovaxp8b8j</sha1>
    </revision>
  </page>
  <page>
    <title>Property:P10</title>
    <ns>862</ns>
    <id>17356</id>
    <revision>
      <id>175496</id>
      <timestamp>2025-08-10T11:07:01Z</timestamp>
      <contributor>
        <username>Immanuelle</username>
        <id>2</id>
      </contributor>
      <comment>/* wbeditentity-create-property:0| */</comment>
      <origin>175496</origin>
      <model>wikibase-property</model>
      <format>application/json</format>
      <text bytes="160" sha1="dbafgwbe0cytkxyf0kgs18sfgg95ot7" xml:space="preserve">{"type":"property","datatype":"monolingualtext","id":"P10","labels":{"en":{"language":"en","value":"Marriage date"}},"descriptions":[],"aliases":[],"claims":[]}</text>
      <sha1>dbafgwbe0cytkxyf0kgs18sfgg95ot7</sha1>
    </revision>
  </page>
  <page>
    <title>Property:P11</title>
    <ns>862</ns>
    <id>17357</id>
    <revision>
      <id>2016747</id>
      <parentid>175497</parentid>
      <timestamp>2025-08-17T18:27:27Z</timestamp>
      <contributor>
        <username>Immanuelle</username>
        <id>2</id>
      </contributor>
      <comment>/* wbsetlabel-set:1|en */ Sex (deprecated)</comment>
      <origin>2016747</origin>
      <model>wikibase-property</model>
      <format>application/json</format>
      <text bytes="163" sha1="3703bqed246m1bihf5272nuaia3dtpi" xml:space="preserve">{"type":"property","datatype":"monolingualtext","id":"P11","labels":{"en":{"language":"en","value":"Sex (deprecated)"}},"descriptions":[],"aliases":[],"claims":[]}</text>
      <sha1>3703bqed246m1bihf5272nuaia3dtpi</sha1>
    </revision>
  </page>
  <page>
    <title>Property:P12</title>
    <ns>862</ns>
    <id>17358</id>
    <revision>
      <id>175498</id>
      <timestamp>2025-08-10T11:07:02Z</timestamp>
      <contributor>
        <username>Immanuelle</username>
        <id>2</id>
      </contributor>
      <comment>/* wbeditentity-create-property:0| */</comment>
      <origin>175498</origin>
      <model>wikibase-property</model>
      <format>application/json</format>
      <text bytes="157" sha1="olo51411dxkqkjs39ymdw83nloh3ef0" xml:space="preserve">{"type":"property","datatype":"monolingualtext","id":"P12","labels":{"en":{"language":"en","value":"Occupation"}},"descriptions":[],"aliases":[],"claims":[]}</text>
      <sha1>olo51411dxkqkjs39ymdw83nloh3ef0</sha1>
    </revision>
  </page>
  <page>
    <title>Property:P13</title>
    <ns>862</ns>
    <id>17359</id>
    <revision>
      <id>175499</id>
      <timestamp>2025-08-10T11:07:03Z</timestamp>
      <contributor>
        <username>Immanuelle</username>
        <id>2</id>
      </contributor>
      <comment>/* wbeditentity-create-property:0| */</comment>
      <origin>175499</origin>
      <model>wikibase-property</model>
      <format>application/json</format>
      <text bytes="156" sha1="nr06ynv1kqph2ka34uvb5642cmdevrs" xml:space="preserve">{"type":"property","datatype":"monolingualtext","id":"P13","labels":{"en":{"language":"en","value":"Residence"}},"descriptions":[],"aliases":[],"claims":[]}</text>
      <sha1>nr06ynv1kqph2ka34uvb5642cmdevrs</sha1>
    </revision>
  </page>
  <page>
    <title>Property:P14</title>
    <ns>862</ns>
    <id>17360</id>
    <revision>
      <id>175500</id>
      <timestamp>2025-08-10T11:07:04Z</timestamp>
      <contributor>
        <username>Immanuelle</username>
        <id>2</id>
      </contributor>
      <comment>/* wbeditentity-create-property:0| */</comment>
      <origin>175500</origin>
      <model>wikibase-property</model>
      <format>application/json</format>
      <text bytes="153" sha1="9j6fyeaqtqu521n7iqhc686el7rkl4g" xml:space="preserve">{"type":"property","datatype":"monolingualtext","id":"P14","labels":{"en":{"language":"en","value":"Source"}},"descriptions":[],"aliases":[],"claims":[]}</text>
      <sha1>9j6fyeaqtqu521n7iqhc686el7rkl4g</sha1>
    </revision>
  </page>
  <page>
    <title>Property:P15</title>
    <ns>862</ns>
    <id>17361</id>
    <revision>
      <id>175501</id>
      <timestamp>2025-08-10T11:07:05Z</timestamp>
      <contributor>
        <username>Immanuelle</username>
        <id>2</id>
      </contributor>
      <comment>/* wbeditentity-create-property:0| */</comment>
      <origin>175501</origin>
      <model>wikibase-property</model>
      <format>application/json</format>
      <text bytes="148" sha1="dc58lrg31edldfu9265qmwexkywwdib" xml:space="preserve">{"type":"property","datatype":"string","id":"P15","labels":{"en":{"language":"en","value":"Notes page"}},"descriptions":[],"aliases":[],"claims":[]}</text>
      <sha1>dc58lrg31edldfu9265qmwexkywwdib</sha1>
    </revision>
  </page>
  <page>
    <title>Property:P16</title>
    <ns>862</ns>
    <id>17362</id>
    <revision>
      <id>175502</id>
      <timestamp>2025-08-10T11:07:06Z</timestamp>
      <contributor>
        <username>Immanuelle</username>
        <id>2</id>
      </contributor>
      <comment>/* wbeditentity-create-property:0| */</comment>
      <origin>175502</origin>
      <model>wikibase-property</model>
      <format>application/json</format>
      <text bytes="158" sha1="b0jdxx3gvivkk8u8rs5vq69p1c841lp" xml:space="preserve">{"type":"property","datatype":"wikibase-item","id":"P16","labels":{"en":{"language":"en","value":"Parent family"}},"descriptions":[],"aliases":[],"claims":[]}</text>
      <sha1>b0jdxx3gvivkk8u8rs5vq69p1c841lp</sha1>
    </revision>
  </page>
  <page>
    <title>Property:P18</title>
    <ns>862</ns>
    <id>17363</id>
    <revision>
      <id>175503</id>
      <timestamp>2025-08-10T11:07:08Z</timestamp>
      <contributor>
        <username>Immanuelle</username>
        <id>2</id>
      </contributor>
      <comment>/* wbeditentity-create-property:0| */</comment>
      <origin>175503</origin>
      <model>wikibase-property</model>
      <format>application/json</format>
      <text bytes="152" sha1="rxn9wd4kxfwekkj99jzysjtam8cj87e" xml:space="preserve">{"type":"property","datatype":"wikibase-item","id":"P18","labels":{"en":{"language":"en","value":"Husband"}},"descriptions":[],"aliases":[],"claims":[]}</text>
      <sha1>rxn9wd4kxfwekkj99jzysjtam8cj87e</sha1>
    </revision>
  </page>
  <page>
    <title>Property:P19</title>
    <ns>862</ns>
    <id>17364</id>
    <revision>
      <id>175504</id>
      <timestamp>2025-08-10T11:07:08Z</timestamp>
      <contributor>
        <username>Immanuelle</username>
        <id>2</id>
      </contributor>
      <comment>/* wbeditentity-create-property:0| */</comment>
      <origin>175504</origin>
      <model>wikibase-property</model>
      <format>application/json</format>
      <text bytes="149" sha1="i4hlgnpzeaglhi1nt6eebf0yaalis2h" xml:space="preserve">{"type":"property","datatype":"wikibase-item","id":"P19","labels":{"en":{"language":"en","value":"Wife"}},"descriptions":[],"aliases":[],"claims":[]}</text>
      <sha1>i4hlgnpzeaglhi1nt6eebf0yaalis2h</sha1>
    </revision>
  </page>
  <page>
    <title>Property:P2</title>
    <ns>862</ns>
    <id>17346</id>
    <revision>
      <id>175480</id>
      <timestamp>2025-08-10T09:14:37Z</timestamp>
      <contributor>
        <username>Immanuelle</username>
        <id>2</id>
      </contributor>
      <comment>/* wbeditentity-create:2|en */ Spouse family</comment>
      <origin>175480</origin>
      <model>wikibase-property</model>
      <format>application/json</format>
      <text bytes="157" sha1="kyqaak94j6mm4tayqxukefhalxuyp82" xml:space="preserve">{"type":"property","datatype":"wikibase-item","id":"P2","labels":{"en":{"language":"en","value":"Spouse family"}},"descriptions":[],"aliases":[],"claims":[]}</text>
      <sha1>kyqaak94j6mm4tayqxukefhalxuyp82</sha1>
    </revision>
  </page>
  <page>
    <title>Property:P20</title>
    <ns>862</ns>
    <id>17365</id>
    <revision>
      <id>175505</id>
      <timestamp>2025-08-10T11:07:09Z</timestamp>
      <contributor>
        <username>Immanuelle</username>
        <id>2</id>
      </contributor>
      <comment>/* wbeditentity-create-property:0| */</comment>
      <origin>175505</origin>
      <model>wikibase-property</model>
      <format>application/json</format>
      <text bytes="150" sha1="1rjmhla3hy9s1fvttekbx15prst17ie" xml:space="preserve">{"type":"property","datatype":"wikibase-item","id":"P20","labels":{"en":{"language":"en","value":"Child"}},"descriptions":[],"aliases":[],"claims":[]}</text>
      <sha1>1rjmhla3hy9s1fvttekbx15prst17ie</sha1>
    </revision>
  </page>
  <page>
    <title>Property:P3</title>
    <ns>862</ns>
    <id>17349</id>
    <revision>
      <id>175489</id>
      <timestamp>2025-08-10T11:06:54Z</timestamp>
      <contributor>
        <username>Immanuelle</username>
        <id>2</id>
      </contributor>
      <comment>/* wbeditentity-create-property:0| */</comment>
      <origin>175489</origin>
      <model>wikibase-property</model>
      <format>application/json</format>
      <text bytes="156" sha1="qvv2kazrfq04gukfagmxd5x0boq62vr" xml:space="preserve">{"type":"property","datatype":"monolingualtext","id":"P3","labels":{"en":{"language":"en","value":"Given name"}},"descriptions":[],"aliases":[],"claims":[]}</text>
      <sha1>qvv2kazrfq04gukfagmxd5x0boq62vr</sha1>
    </revision>
  </page>
  <page>
    <title>Property:P39</title>
    <ns>862</ns>
    <id>17380</id>
    <revision>
      <id>175541</id>
      <timestamp>2025-08-10T11:12:15Z</timestamp>
      <contributor>
        <username>Immanuelle</username>
        <id>2</id>
      </contributor>
      <comment>/* wbeditentity-create:2|en */ instance of</comment>
      <origin>175541</origin>
      <model>wikibase-property</model>
      <format>application/json</format>
      <text bytes="156" sha1="9rfru29c3gjc600clcidpl2vi1rn6zs" xml:space="preserve">{"type":"property","datatype":"wikibase-item","id":"P39","labels":{"en":{"language":"en","value":"instance of"}},"descriptions":[],"aliases":[],"claims":[]}</text>
      <sha1>9rfru29c3gjc600clcidpl2vi1rn6zs</sha1>
    </revision>
  </page>
  <page>
    <title>Property:P4</title>
    <ns>862</ns>
    <id>17350</id>
    <revision>
      <id>175490</id>
      <timestamp>2025-08-10T11:06:55Z</timestamp>
      <contributor>
        <username>Immanuelle</username>
        <id>2</id>
      </contributor>
      <comment>/* wbeditentity-create-property:0| */</comment>
      <origin>175490</origin>
      <model>wikibase-property</model>
      <format>application/json</format>
      <text bytes="153" sha1="6a21h02o1xhtdbeps3f01ieclnbd1iq" xml:space="preserve">{"type":"property","datatype":"monolingualtext","id":"P4","labels":{"en":{"language":"en","value":"Surname"}},"descriptions":[],"aliases":[],"claims":[]}</text>
      <sha1>6a21h02o1xhtdbeps3f01ieclnbd1iq</sha1>
    </revision>
  </page>
  <page>
    <title>Property:P40</title>
    <ns>862</ns>
    <id>28840</id>
    <revision>
      <id>504901</id>
      <parentid>504827</parentid>
      <timestamp>2025-08-12T04:37:52Z</timestamp>
      <contributor>
        <username>Immanuelle</username>
        <id>2</id>
      </contributor>
      <comment>/* wbsetlabel-set:1|en */ Reference number (deprecated?)</comment>
      <origin>504901</origin>
      <model>wikibase-property</model>
      <format>application/json</format>
      <text bytes="260" sha1="dpkcbwzyh6p9luvgau2xa6gbyu0nmy2" xml:space="preserve">{"type":"property","datatype":"string","id":"P40","labels":{"en":{"language":"en","value":"Reference number (deprecated?)"}},"descriptions":{"en":{"language":"en","value":"External reference number or identifier (GEDCOM REFN field)"}},"aliases":[],"claims":[]}</text>
      <sha1>dpkcbwzyh6p9luvgau2xa6gbyu0nmy2</sha1>
    </revision>
  </page>
  <page>
    <title>Property:P41</title>
    <ns>862</ns>
    <id>28912</id>
    <revision>
      <id>222722</id>
      <timestamp>2025-08-10T21:16:27Z</timestamp>
      <contributor>
        <username>Immanuelle</username>
        <id>2</id>
      </contributor>
      <comment>/* wbeditentity-create-property:0| */</comment>
      <origin>222722</origin>
      <model>wikibase-property</model>
      <format>application/json</format>
      <text bytes="206" sha1="p49b4ij2x8kbyf91i4zfvff34018mup" xml:space="preserve">{"type":"property","datatype":"string","id":"P41","labels":{"en":{"language":"en","value":"GEDCOM REFN"}},"descriptions":{"en":{"language":"en","value":"GEDCOM gedcom_refn field"}},"aliases":[],"claims":[]}</text>
      <sha1>p49b4ij2x8kbyf91i4zfvff34018mup</sha1>
    </revision>
  </page>
  <page>
    <title>Property:P42</title>
    <ns>862</ns>
    <id>28913</id>
    <revision>
      <id>1263333</id>
      <parentid>222723</parentid>
      <timestamp>2025-08-15T23:10:13Z</timestamp>
      <contributor>
        <username>Immanuelle</username>
        <id>2</id>
      </contributor>
      <comment>/* wbsetdescription-set:1|en */ This is not a gedcom field, idk why the fuck the ai thought it was, it is explicitly wikidata based</comment>
      <origin>1263333</origin>
      <model>wikibase-property</model>
      <format>application/json</format>
      <text bytes="283" sha1="i5kh5hk8ej33j75y5bh419ycvnidxuv" xml:space="preserve">{"type":"property","datatype":"wikibase-item","id":"P42","labels":{"en":{"language":"en","value":"Spouse"}},"descriptions":{"en":{"language":"en","value":"This is not a gedcom field, idk why the fuck the ai thought it was, it is explicitly wikidata based"}},"aliases":[],"claims":[]}</text>
      <sha1>i5kh5hk8ej33j75y5bh419ycvnidxuv</sha1>
    </revision>
  </page>
  <page>
    <title>Property:P43</title>
    <ns>862</ns>
    <id>51532</id>
    <revision>
      <id>1520803</id>
      <parentid>273318</parentid>
      <timestamp>2025-08-16T18:52:40Z</timestamp>
      <contributor>
        <username>Immanuelle</username>
        <id>2</id>
      </contributor>
      <comment>/* wbsetaliases-add:1|en */ geni.com profile ID</comment>
      <origin>1520803</origin>
      <model>wikibase-property</model>
      <format>application/json</format>
      <text bytes="211" sha1="81rfji5950nl7w3r5omnehw3khsozva" xml:space="preserve">{"type":"property","datatype":"string","id":"P43","labels":{"en":{"language":"en","value":"Geni.com profile ID"}},"descriptions":[],"aliases":{"en":[{"language":"en","value":"geni.com profile ID"}]},"claims":[]}</text>
      <sha1>81rfji5950nl7w3r5omnehw3khsozva</sha1>
    </revision>
  </page>
  <page>
    <title>Property:P44</title>
    <ns>862</ns>
    <id>51627</id>
    <revision>
      <id>273565</id>
      <timestamp>2025-08-11T07:42:41Z</timestamp>
      <contributor>
        <username>Immanuelle</username>
        <id>2</id>
      </contributor>
      <comment>/* wbeditentity-create:2|en */ Wikidata ID</comment>
      <origin>273565</origin>
      <model>wikibase-property</model>
      <format>application/json</format>
      <text bytes="149" sha1="kt8sw2qrkrbk60zcxlmorn71ach7v01" xml:space="preserve">{"type":"property","datatype":"string","id":"P44","labels":{"en":{"language":"en","value":"Wikidata ID"}},"descriptions":[],"aliases":[],"claims":[]}</text>
      <sha1>kt8sw2qrkrbk60zcxlmorn71ach7v01</sha1>
    </revision>
  </page>
  <page>
    <title>Property:P45</title>
    <ns>862</ns>
    <id>52407</id>
    <revision>
      <id>275600</id>
      <timestamp>2025-08-11T07:53:39Z</timestamp>
      <contributor>
        <username>Immanuelle</username>
        <id>2</id>
      </contributor>
      <comment>/* wbeditentity-create:2|en */ Described at url</comment>
      <origin>275600</origin>
      <model>wikibase-property</model>
      <format>application/json</format>
      <text bytes="151" sha1="15emynxf3hwim1fxf15fi5q4v8hn0hr" xml:space="preserve">{"type":"property","datatype":"url","id":"P45","labels":{"en":{"language":"en","value":"Described at url"}},"descriptions":[],"aliases":[],"claims":[]}</text>
      <sha1>15emynxf3hwim1fxf15fi5q4v8hn0hr</sha1>
    </revision>
  </page>
  <page>
    <title>Property:P46</title>
    <ns>862</ns>
    <id>104998</id>
    <revision>
      <id>419151</id>
      <timestamp>2025-08-11T22:37:37Z</timestamp>
      <contributor>
        <username>Immanuelle</username>
        <id>2</id>
      </contributor>
      <comment>/* wbeditentity-create:2|en */ notes page</comment>
      <origin>419151</origin>
      <model>wikibase-property</model>
      <format>application/json</format>
      <text bytes="145" sha1="su8qadqg2zrkefvzypx6h4fv49kbie5" xml:space="preserve">{"type":"property","datatype":"url","id":"P46","labels":{"en":{"language":"en","value":"notes page"}},"descriptions":[],"aliases":[],"claims":[]}</text>
      <sha1>su8qadqg2zrkefvzypx6h4fv49kbie5</sha1>
    </revision>
  </page>
  <page>
    <title>Property:P47</title>
    <ns>862</ns>
    <id>125462</id>
    <revision>
      <id>495685</id>
      <timestamp>2025-08-12T04:12:33Z</timestamp>
      <contributor>
        <username>Immanuelle</username>
        <id>2</id>
      </contributor>
      <comment>/* wbeditentity-create-property:0| */</comment>
      <origin>495685</origin>
      <model>wikibase-property</model>
      <format>application/json</format>
      <text bytes="210" sha1="ebqcd01va1mfl38ytx29kv2z8ymirik" xml:space="preserve">{"type":"property","datatype":"wikibase-item","id":"P47","labels":{"en":{"language":"en","value":"Father"}},"descriptions":{"en":{"language":"en","value":"Male parent of the subject"}},"aliases":[],"claims":[]}</text>
      <sha1>ebqcd01va1mfl38ytx29kv2z8ymirik</sha1>
    </revision>
  </page>
  <page>
    <title>Property:P48</title>
    <ns>862</ns>
    <id>125465</id>
    <revision>
      <id>495691</id>
      <timestamp>2025-08-12T04:12:35Z</timestamp>
      <contributor>
        <username>Immanuelle</username>
        <id>2</id>
      </contributor>
      <comment>/* wbeditentity-create-property:0| */</comment>
      <origin>495691</origin>
      <model>wikibase-property</model>
      <format>application/json</format>
      <text bytes="212" sha1="p0blxwjojakrjov6xta1t062im7v34j" xml:space="preserve">{"type":"property","datatype":"wikibase-item","id":"P48","labels":{"en":{"language":"en","value":"Mother"}},"descriptions":{"en":{"language":"en","value":"Female parent of the subject"}},"aliases":[],"claims":[]}</text>
      <sha1>p0blxwjojakrjov6xta1t062im7v34j</sha1>
    </revision>
  </page>
  <page>
    <title>Property:P49</title>
    <ns>862</ns>
    <id>180417</id>
    <revision>
      <id>827653</id>
      <timestamp>2025-08-13T11:21:58Z</timestamp>
      <contributor>
        <username>Immanuelle</username>
        <id>2</id>
      </contributor>
      <comment>/* wbeditentity-create-property:0| */</comment>
      <origin>827653</origin>
      <model>wikibase-property</model>
      <format>application/json</format>
      <text bytes="255" sha1="mb0oitr4856dkquaqhbqk7ibqs4gupj" xml:space="preserve">{"type":"property","datatype":"quantity","id":"P49","labels":{"en":{"language":"en","value":"ordinal within year"}},"descriptions":{"en":{"language":"en","value":"position of this day within the year (1-364 for Gaiad calendar)"}},"aliases":[],"claims":[]}</text>
      <sha1>mb0oitr4856dkquaqhbqk7ibqs4gupj</sha1>
    </revision>
  </page>
  <page>
    <title>Property:P5</title>
    <ns>862</ns>
    <id>17351</id>
    <revision>
      <id>175491</id>
      <timestamp>2025-08-10T11:06:56Z</timestamp>
      <contributor>
        <username>Immanuelle</username>
        <id>2</id>
      </contributor>
      <comment>/* wbeditentity-create-property:0| */</comment>
      <origin>175491</origin>
      <model>wikibase-property</model>
      <format>application/json</format>
      <text bytes="155" sha1="1qdcz3a1o8zuwkxavp7knatl64sfnji" xml:space="preserve">{"type":"property","datatype":"monolingualtext","id":"P5","labels":{"en":{"language":"en","value":"Full name"}},"descriptions":[],"aliases":[],"claims":[]}</text>
      <sha1>1qdcz3a1o8zuwkxavp7knatl64sfnji</sha1>
    </revision>
  </page>
  <page>
    <title>Property:P50</title>
    <ns>862</ns>
    <id>180418</id>
    <revision>
      <id>827660</id>
      <timestamp>2025-08-13T11:21:59Z</timestamp>
      <contributor>
        <username>Immanuelle</username>
        <id>2</id>
      </contributor>
      <comment>/* wbeditentity-create-property:0| */</comment>
      <origin>827660</origin>
      <model>wikibase-property</model>
      <format>application/json</format>
      <text bytes="256" sha1="5ulo0i2wp7apxzjarbsfg8u6mdoabw3" xml:space="preserve">{"type":"property","datatype":"quantity","id":"P50","labels":{"en":{"language":"en","value":"ordinal within month"}},"descriptions":{"en":{"language":"en","value":"position of this day within its month (1-28 for Gaiad calendar)"}},"aliases":[],"claims":[]}</text>
      <sha1>5ulo0i2wp7apxzjarbsfg8u6mdoabw3</sha1>
    </revision>
  </page>
  <page>
    <title>Property:P51</title>
    <ns>862</ns>
    <id>180419</id>
    <revision>
      <id>827665</id>
      <timestamp>2025-08-13T11:22:01Z</timestamp>
      <contributor>
        <username>Immanuelle</username>
        <id>2</id>
      </contributor>
      <comment>/* wbeditentity-create-property:0| */</comment>
      <origin>827665</origin>
      <model>wikibase-property</model>
      <format>application/json</format>
      <text bytes="244" sha1="fncd38xl1bbgt7ffs1k47zd7zc23xt7" xml:space="preserve">{"type":"property","datatype":"quantity","id":"P51","labels":{"en":{"language":"en","value":"ISO week number"}},"descriptions":{"en":{"language":"en","value":"ISO 8601 week number that this day corresponds to (1-52)"}},"aliases":[],"claims":[]}</text>
      <sha1>fncd38xl1bbgt7ffs1k47zd7zc23xt7</sha1>
    </revision>
  </page>
  <page>
    <title>Property:P52</title>
    <ns>862</ns>
    <id>180420</id>
    <revision>
      <id>827668</id>
      <timestamp>2025-08-13T11:22:02Z</timestamp>
      <contributor>
        <username>Immanuelle</username>
        <id>2</id>
      </contributor>
      <comment>/* wbeditentity-create-property:0| */</comment>
      <origin>827668</origin>
      <model>wikibase-property</model>
      <format>application/json</format>
      <text bytes="235" sha1="cmov6sy2zk74sbhxkp00vsiosdwy0ih" xml:space="preserve">{"type":"property","datatype":"quantity","id":"P52","labels":{"en":{"language":"en","value":"ISO weekday number"}},"descriptions":{"en":{"language":"en","value":"ISO 8601 weekday number (1=Monday, 7=Sunday)"}},"aliases":[],"claims":[]}</text>
      <sha1>cmov6sy2zk74sbhxkp00vsiosdwy0ih</sha1>
    </revision>
  </page>
  <page>
    <title>Property:P53</title>
    <ns>862</ns>
    <id>190709</id>
    <revision>
      <id>950783</id>
      <timestamp>2025-08-14T03:07:54Z</timestamp>
      <contributor>
        <username>Immanuelle</username>
        <id>2</id>
      </contributor>
      <comment>/* wbeditentity-create:2|en */ Wikidata Identifier</comment>
      <origin>950783</origin>
      <model>wikibase-property</model>
      <format>application/json</format>
      <text bytes="162" sha1="m6ijn5zkddi2ie6yks78wghlvn1pkkq" xml:space="preserve">{"type":"property","datatype":"external-id","id":"P53","labels":{"en":{"language":"en","value":"Wikidata Identifier"}},"descriptions":[],"aliases":[],"claims":[]}</text>
      <sha1>m6ijn5zkddi2ie6yks78wghlvn1pkkq</sha1>
    </revision>
  </page>
  <page>
    <title>Property:P54</title>
    <ns>862</ns>
    <id>190778</id>
    <revision>
      <id>975048</id>
      <timestamp>2025-08-14T06:16:36Z</timestamp>
      <contributor>
        <username>Immanuelle</username>
        <id>2</id>
      </contributor>
      <comment>/* wbeditentity-create-property:0| */</comment>
      <origin>975048</origin>
      <model>wikibase-property</model>
      <format>application/json</format>
      <text bytes="210" sha1="kkfgmqqi5kgnyc8wd3j3w3pvi8oxl1r" xml:space="preserve">{"type":"property","datatype":"string","id":"P54","labels":{"en":{"language":"en","value":"suffix"}},"descriptions":{"en":{"language":"en","value":"name suffix (Jr., Sr., III, etc.)"}},"aliases":[],"claims":[]}</text>
      <sha1>kkfgmqqi5kgnyc8wd3j3w3pvi8oxl1r</sha1>
    </revision>
  </page>
  <page>
    <title>Property:P55</title>
    <ns>862</ns>
    <id>192009</id>
    <revision>
      <id>2015956</id>
      <timestamp>2025-08-17T18:24:36Z</timestamp>
      <contributor>
        <username>Immanuelle</username>
        <id>2</id>
      </contributor>
      <comment>/* wbeditentity-create:2|en */ Sex (object)</comment>
      <origin>2015956</origin>
      <model>wikibase-property</model>
      <format>application/json</format>
      <text bytes="157" sha1="p8wyi2t7jsk4stw94q748abrmzfwoq2" xml:space="preserve">{"type":"property","datatype":"wikibase-item","id":"P55","labels":{"en":{"language":"en","value":"Sex (object)"}},"descriptions":[],"aliases":[],"claims":[]}</text>
      <sha1>p8wyi2t7jsk4stw94q748abrmzfwoq2</sha1>
    </revision>
  </page>
  <page>
    <title>Property:P56</title>
    <ns>862</ns>
    <id>192010</id>
    <revision>
      <id>2017898</id>
      <timestamp>2025-08-17T18:31:25Z</timestamp>
      <contributor>
        <username>Immanuelle</username>
        <id>2</id>
      </contributor>
      <comment>/* wbeditentity-create:2|en */ Date of Birth</comment>
      <origin>2017898</origin>
      <model>wikibase-property</model>
      <format>application/json</format>
      <text bytes="149" sha1="qzviw12f7i3sb5p3wfkc9dz44yfg5bq" xml:space="preserve">{"type":"property","datatype":"time","id":"P56","labels":{"en":{"language":"en","value":"Date of Birth"}},"descriptions":[],"aliases":[],"claims":[]}</text>
      <sha1>qzviw12f7i3sb5p3wfkc9dz44yfg5bq</sha1>
    </revision>
  </page>
  <page>
    <title>Property:P57</title>
    <ns>862</ns>
    <id>192011</id>
    <revision>
      <id>2019508</id>
      <timestamp>2025-08-17T18:37:24Z</timestamp>
      <contributor>
        <username>Immanuelle</username>
        <id>2</id>
      </contributor>
      <comment>/* wbeditentity-create:2|en */ Date of Death</comment>
      <origin>2019508</origin>
      <model>wikibase-property</model>
      <format>application/json</format>
      <text bytes="149" sha1="94fkb0mdr5wbnv3n8z1qhfxsz2p4r5m" xml:space="preserve">{"type":"property","datatype":"time","id":"P57","labels":{"en":{"language":"en","value":"Date of Death"}},"descriptions":[],"aliases":[],"claims":[]}</text>
      <sha1>94fkb0mdr5wbnv3n8z1qhfxsz2p4r5m</sha1>
    </revision>
  </page>
  <page>
    <title>Property:P58</title>
    <ns>862</ns>
    <id>192012</id>
    <revision>
      <id>2023857</id>
      <timestamp>2025-08-17T18:53:49Z</timestamp>
      <contributor>
        <username>Immanuelle</username>
        <id>2</id>
      </contributor>
      <comment>/* wbeditentity-create:2|en */ Image</comment>
      <origin>2023857</origin>
      <model>wikibase-property</model>
      <format>application/json</format>
      <text bytes="149" sha1="4gx2wmdqtxh5y804mn69klfbm77l467" xml:space="preserve">{"type":"property","datatype":"commonsMedia","id":"P58","labels":{"en":{"language":"en","value":"Image"}},"descriptions":[],"aliases":[],"claims":[]}</text>
      <sha1>4gx2wmdqtxh5y804mn69klfbm77l467</sha1>
    </revision>
  </page>
  <page>
    <title>Property:P59</title>
    <ns>862</ns>
    <id>192014</id>
    <revision>
      <id>2049186</id>
      <parentid>2048913</parentid>
      <timestamp>2025-08-17T20:29:01Z</timestamp>
      <contributor>
        <username>Immanuelle</username>
        <id>2</id>
      </contributor>
      <comment>/* wbsetaliases-add:1|en */ cladoplast of</comment>
      <origin>2049186</origin>
      <model>wikibase-property</model>
      <format>application/json</format>
      <text bytes="300" sha1="4cbpad5qbpvbn0k7qyqz060fjcbun23" xml:space="preserve">{"type":"property","datatype":"external-id","id":"P59","labels":{"en":{"language":"en","value":"Cladoplast of"}},"descriptions":{"en":{"language":"en","value":"Link to the wikidata entry of the thing this is a cladoplast of"}},"aliases":{"en":[{"language":"en","value":"cladoplast of"}]},"claims":[]}</text>
      <sha1>4cbpad5qbpvbn0k7qyqz060fjcbun23</sha1>
    </revision>
  </page>
  <page>
    <title>Property:P6</title>
    <ns>862</ns>
    <id>17352</id>
    <revision>
      <id>175492</id>
      <timestamp>2025-08-10T11:06:57Z</timestamp>
      <contributor>
        <username>Immanuelle</username>
        <id>2</id>
      </contributor>
      <comment>/* wbeditentity-create-property:0| */</comment>
      <origin>175492</origin>
      <model>wikibase-property</model>
      <format>application/json</format>
      <text bytes="160" sha1="3lq49znt0fp177q72orf530zplb92l1" xml:space="preserve">{"type":"property","datatype":"monolingualtext","id":"P6","labels":{"en":{"language":"en","value":"Alternate name"}},"descriptions":[],"aliases":[],"claims":[]}</text>
      <sha1>3lq49znt0fp177q72orf530zplb92l1</sha1>
    </revision>
  </page>
  <page>
    <title>Property:P60</title>
    <ns>862</ns>
    <id>192017</id>
    <revision>
      <id>2159661</id>
      <timestamp>2025-08-18T02:06:04Z</timestamp>
      <contributor>
        <username>Immanuelle</username>
        <id>2</id>
      </contributor>
      <comment>/* wbeditentity-create:2|en */ uuid refn</comment>
      <origin>2159661</origin>
      <model>wikibase-property</model>
      <format>application/json</format>
      <text bytes="147" sha1="f1dps68169ob5r5dac2w9lkz37is7do" xml:space="preserve">{"type":"property","datatype":"string","id":"P60","labels":{"en":{"language":"en","value":"uuid refn"}},"descriptions":[],"aliases":[],"claims":[]}</text>
      <sha1>f1dps68169ob5r5dac2w9lkz37is7do</sha1>
    </revision>
  </page>
  <page>
    <title>Property:P7</title>
    <ns>862</ns>
    <id>17353</id>
    <revision>
      <id>2019579</id>
      <parentid>175493</parentid>
      <timestamp>2025-08-17T18:37:39Z</timestamp>
      <contributor>
        <username>Immanuelle</username>
        <id>2</id>
      </contributor>
      <comment>/* wbsetlabel-set:1|en */ Birth date (deprecated)</comment>
      <origin>2019579</origin>
      <model>wikibase-property</model>
      <format>application/json</format>
      <text bytes="169" sha1="qu1539ms61fougajicpcryd8aiil9rw" xml:space="preserve">{"type":"property","datatype":"monolingualtext","id":"P7","labels":{"en":{"language":"en","value":"Birth date (deprecated)"}},"descriptions":[],"aliases":[],"claims":[]}</text>
      <sha1>qu1539ms61fougajicpcryd8aiil9rw</sha1>
    </revision>
  </page>
  <page>
    <title>Property:P8</title>
    <ns>862</ns>
    <id>17354</id>
    <revision>
      <id>2019621</id>
      <parentid>175494</parentid>
      <timestamp>2025-08-17T18:37:46Z</timestamp>
      <contributor>
        <username>Immanuelle</username>
        <id>2</id>
      </contributor>
      <comment>/* wbsetlabel-set:1|en */ Death date (deprecated)</comment>
      <origin>2019621</origin>
      <model>wikibase-property</model>
      <format>application/json</format>
      <text bytes="169" sha1="j0yxwkwt6keh1902huvwrj9cbh484xm" xml:space="preserve">{"type":"property","datatype":"monolingualtext","id":"P8","labels":{"en":{"language":"en","value":"Death date (deprecated)"}},"descriptions":[],"aliases":[],"claims":[]}</text>
      <sha1>j0yxwkwt6keh1902huvwrj9cbh484xm</sha1>
    </revision>
  </page>
  <page>
    <title>Property:P9</title>
    <ns>862</ns>
    <id>17355</id>
    <revision>
      <id>175495</id>
      <timestamp>2025-08-10T11:07:00Z</timestamp>
      <contributor>
        <username>Immanuelle</username>
        <id>2</id>
      </contributor>
      <comment>/* wbeditentity-create-property:0| */</comment>
      <origin>175495</origin>
      <model>wikibase-property</model>
      <format>application/json</format>
      <text bytes="157" sha1="h4cnl8ujbcsj8h2rzmw54pfu2tivncz" xml:space="preserve">{"type":"property","datatype":"monolingualtext","id":"P9","labels":{"en":{"language":"en","value":"Burial date"}},"descriptions":[],"aliases":[],"claims":[]}</text>
      <sha1>h4cnl8ujbcsj8h2rzmw54pfu2tivncz</sha1>
    </revision>
  </page>
</mediawiki>
